AUTHORS.rst
CONTRIBUTING.rst
HISTORY.rst
LICENSE
MANIFEST.in
README.rst
setup.py
dingos/__init__.py
dingos/admin.py
dingos/filter.py
dingos/forms.py
dingos/import_handling.py
dingos/importer.py
dingos/models.py
dingos/read_settings.py
dingos/urls.py
dingos/validators.py
dingos/view_classes.py
dingos/views.py
dingos/core/__init__.py
dingos/core/datastructures.py
dingos/core/decorators.py
dingos/core/extractors.py
dingos/core/http_helpers.py
dingos/core/template_helpers.py
dingos/core/utilities.py
dingos/core/xml_utils.py
dingos/management/__init__.py
dingos/management/commands/__init__.py
dingos/management/commands/dingos_generic_xml_import.py
dingos/management/commands/dingos_manage_naming_schemas.py
dingos/management/commands/dingos_manage_user_settings.py
dingos/management/commands/dingos_regenerate_iobject_names.py
dingos/migrations/0001_initial.py
dingos/migrations/0002_auto__add_field_factvalue_value_on_disk__del_unique_factvalue_value_fa.py
dingos/migrations/0003_auto__del_field_factvalue_value_on_disk__add_field_factvalue_storage_l.py
dingos/migrations/0004_auto__add_blobstorage.py
dingos/migrations/0005_auto__del_field_blobstorage__content__add_field_blobstorage_content.py
dingos/migrations/0006_rename_field_factdatatype_name_space__to__factdatatype_namesp.py
dingos/migrations/0007_auto__add_userdata__add_unique_userdata_user_data_kind.py
dingos/migrations/0008_auto__add_field_userdata_group__chg_field_userdata_user__del_unique_us.py
dingos/migrations/0009_auto__add_positionalnamespace__add_facttermnamespacemap__add_field_inf.py
dingos/migrations/__init__.py
dingos/templates/dingos/grappelli/base.html
dingos/templates/dingos/grappelli/actions/XMLImport.html
dingos/templates/dingos/grappelli/details/InfoObjectDetails.html
dingos/templates/dingos/grappelli/details/base_details.html
dingos/templates/dingos/grappelli/edits/InfoObjectsEdit.html
dingos/templates/dingos/grappelli/edits/SavedSearchesEdit.html
dingos/templates/dingos/grappelli/edits/base_edits.html
django_dingos.egg-info/PKG-INFO
django_dingos.egg-info/SOURCES.txt
django_dingos.egg-info/dependency_links.txt
django_dingos.egg-info/not-zip-safe
django_dingos.egg-info/requires.txt
django_dingos.egg-info/top_level.txt