Metadata-Version: 1.1
Name: django-dingos
Version: 0.2.1
Summary: A Django app that provides a generic framework for managing structured information in a generic way.
Home-page: https://github.com/siemens/django-dingos
Author: Siemens
Author-email: mantis.cert@siemens.com
License: GPLv2+
Keywords: django-dingos
Platform: UNKNOWN
Classifier: Development Status :: 3 - Alpha
Classifier: Framework :: Django
Classifier: Intended Audience :: Developers
Classifier: License :: OSI Approved :: GNU General Public License v2 or later (GPLv2+)
Classifier: Natural Language :: English
Classifier: Programming Language :: Python :: 2.7
Classifier: Topic :: Security
